Metadata-Version: 1.1
Name: NOTMENOTME
Version: 0.4.2
Summary: NOTMENOTME
Home-page: UNKNOWN
Author: NOTMENOTME
Author-email: armannikoopour@gmail.com
License: MIT
Keywords: NOTMENOTME
Platform: UNKNOWN
Classifier: Development Status :: 5 - Production/Stable
Classifier: Intended Audience :: Education
Classifier: Operating System :: Microsoft :: Windows :: Windows 10
Classifier: License :: OSI Approved :: MIT License
Classifier: Programming Language :: Python :: 3
